traffic_cop_client/__init__.py
traffic_cop_client/client.py
traffic_cop_client-0.1.0.dist-info/licenses/LICENSE
traffic_cop_client-0.1.0.dist-info/METADATA
traffic_cop_client-0.1.0.dist-info/WHEEL
traffic_cop_client-0.1.0.dist-info/top_level.txt
traffic_cop_client-0.1.0.dist-info/RECORD
