Metadata-Version: 2.4
Name: traffic-cop-client
Version: 0.1.0
Summary: Python client for Traffic Cop API, an intelligent middleware for optimizing LLM API usage
Author-email: Traffic Cop Team <support@trafficcop.ai>
License: MIT
Project-URL: Homepage, https://trafficcop.ai
Project-URL: Documentation, https://docs.trafficcop.ai
Project-URL: Repository, https://github.com/traffic-cop/traffic-cop-python-sdk
Project-URL: Bug Tracker, https://github.com/traffic-cop/traffic-cop-python-sdk/issues
Project-URL: Changelog, https://github.com/traffic-cop/traffic-cop-python-sdk/blob/main/CHANGELOG.md
Keywords: llm,ai,middleware,traffic-cop,openai,anthropic,claude,gpt,machine-learning
Classifier: Development Status :: 4 - Beta
Classifier: Intended Audience :: Developers
Classifier: License :: OSI Approved :: MIT License
Classifier: Programming Language :: Python :: 3
Classifier: Programming Language :: Python :: 3.9
Classifier: Programming Language :: Python :: 3.10
Classifier: Programming Language :: Python :: 3.11
Classifier: Operating System :: OS Independent
Classifier: Topic :: Software Development :: Libraries :: Python Modules
Classifier: Topic :: Scientific/Engineering :: Artificial Intelligence
Requires-Python: >=3.9
License-File: LICENSE
Requires-Dist: httpx>=0.24.0
Requires-Dist: traffic-cop-common
Provides-Extra: dev
Requires-Dist: pytest>=7.0.0; extra == "dev"
Requires-Dist: pytest-asyncio>=0.21.0; extra == "dev"
Requires-Dist: pytest-cov>=4.1.0; extra == "dev"
Requires-Dist: black>=23.0.0; extra == "dev"
Requires-Dist: isort>=5.12.0; extra == "dev"
Requires-Dist: mypy>=1.0.0; extra == "dev"
Requires-Dist: ruff>=0.0.270; extra == "dev"
Requires-Dist: build>=0.10.0; extra == "dev"
Requires-Dist: twine>=4.0.2; extra == "dev"
Provides-Extra: test
Requires-Dist: pytest>=7.0.0; extra == "test"
Requires-Dist: pytest-asyncio>=0.21.0; extra == "test"
Requires-Dist: pytest-cov>=4.1.0; extra == "test"
Provides-Extra: lint
Requires-Dist: black>=23.0.0; extra == "lint"
Requires-Dist: isort>=5.12.0; extra == "lint"
Requires-Dist: mypy>=1.0.0; extra == "lint"
Requires-Dist: ruff>=0.0.270; extra == "lint"
Dynamic: license-file
